aurora_trinity-1.1.1.dist-info/licenses/LICENSE
trinity_3/__init__.py
trinity_3/core.py
trinity_3/core_backup.py
trinity_3/core_clean.py
trinity_3/hf_integration.py
trinity_3/trigate.py
aurora_trinity-1.1.1.dist-info/METADATA
aurora_trinity-1.1.1.dist-info/WHEEL
aurora_trinity-1.1.1.dist-info/top_level.txt
aurora_trinity-1.1.1.dist-info/RECORD
