Metadata-Version: 2.4
Name: aurora-trinity
Version: 1.1.1
Summary: Aurora Trinity-3: Fractal, Ethical, Free Electronic Intelligence
Home-page: https://github.com/Aurora-Program/Trinity-3
Author: Aurora Alliance
Author-email: contacto@aurora-program.org
License: Apache-2.0
Project-URL: Bug Reports, https://github.com/Aurora-Program/Trinity-3/issues
Project-URL: Source, https://github.com/Aurora-Program/Trinity-3
Project-URL: Documentation, https://github.com/Aurora-Program/Trinity-3/blob/main/README.md
Keywords: ai,ternary-logic,fractal,neural-networks,knowledge-base,ethical-ai
Classifier: Development Status :: 5 - Production/Stable
Classifier: Programming Language :: Python :: 3
Classifier: Programming Language :: Python :: 3.8
Classifier: Programming Language :: Python :: 3.9
Classifier: Programming Language :: Python :: 3.10
Classifier: Programming Language :: Python :: 3.11
Classifier: Programming Language :: Python :: 3.12
Classifier: License :: OSI Approved :: Apache Software License
Classifier: Operating System :: OS Independent
Classifier: Intended Audience :: Science/Research
Classifier: Intended Audience :: Developers
Classifier: Topic :: Scientific/Engineering :: Artificial Intelligence
Classifier: Topic :: Software Development :: Libraries :: Python Modules
Classifier: Natural Language :: English
Classifier: Natural Language :: Spanish
Requires-Python: >=3.8
License-File: LICENSE
Dynamic: author
Dynamic: author-email
Dynamic: classifier
Dynamic: description
Dynamic: description-content-type
Dynamic: home-page
Dynamic: keywords
Dynamic: license
Dynamic: license-file
Dynamic: project-url
Dynamic: requires-python
Dynamic: summary
